classical_logic/__init__.py
classical_logic/core.py
classical_logic/parsing.py
classical_logic-0.1.1.dist-info/LICENSE
classical_logic-0.1.1.dist-info/METADATA
classical_logic-0.1.1.dist-info/WHEEL
classical_logic-0.1.1.dist-info/RECORD
